{"lastModified":1755689479622,"japaCount":0,"roundCount":28,"roundTripCount":0,"strikes":0,"japaDurations":"[]","lastJapaTimestamp":1755689454494,"lastRoundTimestamp":null,"roundData":"[{\"cost\":15,\"strikes\":0,\"time\":1755678233891},{\"cost\":15,\"strikes\":0,\"time\":1755678645650},{\"cost\":15,\"strikes\":2,\"time\":1755679102593},{\"cost\":15,\"strikes\":0,\"time\":1755679478603},{\"cost\":15,\"strikes\":0,\"time\":1755679883266},{\"cost\":15,\"strikes\":0,\"time\":1755680283431},{\"cost\":15,\"strikes\":0,\"time\":1755680693360},{\"cost\":15,\"strikes\":0,\"time\":1755681093839},{\"cost\":15,\"strikes\":0,\"time\":1755681525132},{\"cost\":15,\"strikes\":0,\"time\":1755681918455},{\"cost\":15,\"strikes\":0,\"time\":1755682310241},{\"cost\":15,\"strikes\":0,\"time\":1755682687009},{\"cost\":15,\"strikes\":0,\"time\":1755683089653},{\"cost\":15,\"strikes\":0,\"time\":1755683494073},{\"cost\":15,\"strikes\":0,\"time\":1755683887011},{\"cost\":15,\"strikes\":0,\"time\":1755684290653},{\"cost\":15,\"strikes\":0,\"time\":1755684695435},{\"cost\":15,\"strikes\":0,\"time\":1755685112900},{\"cost\":15,\"strikes\":0,\"time\":1755685511863},{\"cost\":15,\"strikes\":0,\"time\":1755685902026},{\"cost\":15,\"strikes\":0,\"time\":1755686276164},{\"cost\":15,\"strikes\":0,\"time\":1755686677031},{\"cost\":15,\"strikes\":0,\"time\":1755687079913},{\"cost\":15,\"strikes\":0,\"time\":1755687476451},{\"cost\":13,\"strikes\":0,\"time\":1755687878765},{\"cost\":13,\"strikes\":1,\"time\":1755688290728},{\"cost\":13,\"strikes\":0,\"time\":1755688683453},{\"cost\":13,\"strikes\":0,\"time\":1755689454494}]","goal":32}